Workbook
Name Category_List: Lists!$D$5:$D$13
Name Channel_List: Lists!$E$5:$E$9
Name Priority_List: Lists!$B$5:$B$8
Name SLA_Days: Lists!$C$5:$C$8
Name Status_List: Lists!$A$5:$A$11
Name YesNo_List: Lists!$F$5:$F$6

Sheet How to Use
A1: International Customer Support Simulation - Tracker Guide | B1: International Customer Support Simulation - Tracker Guide
A3: Purpose | B3: Log, prioritize and follow up customer tickets from 20 international scenarios, and practice professional, culturally aware support.
A4: Compatibility | B4: Saved as .xlsx and tested for Microsoft Excel 2007: only 2007-era functions (IF, INDEX, MATCH, COUNTIF, AVERAGEIF, IFERROR) are used. No macros.
A5: Sheets
A6: Support Tracker | B6: Main tracker: Customer ID, Issue Category, Priority, Ticket Status, Resolution, Escalation, Follow-up Date + SLA and alerts. Room for 200 tickets (rows 5-204).
A7: Customer Scenarios | B7: 20 customer cases with message, challenge, skills tested, model answer and whether escalation is needed.
A8: Dashboard | B8: Live counts and charts: status, priority, category, escalations, overdue follow-ups, SLA.
A9: Lists | B9: Dropdown choices and SLA days per priority. Edit here to customize.
A10: Colour legend
A11: Yellow cells | B11: Input cells - type, or pick from the dropdown.
A12: Grey cells | B12: Automatic formulas (Days Open, SLA Target, SLA Status, Follow-up Alert) - do not overwrite.
A13: Priority colours | B13: Critical = dark red, High = orange, Medium = yellow, Low = green.
A14: Workflow
A15: Step 1 | B15: Read a scenario on 'Customer Scenarios'. Each has a matching ticket (same Customer ID) already created in the tracker with status New.
A16: Step 2 | B16: Set Ticket Status, enter your name as Assigned Agent, and type your Resolution / Action Taken.
A17: Step 3 | B17: If the case needs a supervisor or specialist team, set Escalated? = Yes and describe the team and reason.
A18: Step 4 | B18: Enter a Follow-up Date. The Follow-up Alert shows Upcoming, Due Today or OVERDUE. When solved, set status to Resolved and enter Date Resolved.
A19: Step 5 | B19: Compare your answer with the model handling, then review the Dashboard.
A20: Assumptions | B20: Company 'GlobeCart' is fictional. SLA days (Critical 1, High 2, Medium 3, Low 5) and the 30-day return policy are assumptions you can change on 'Lists'. Rows 5-10 contain sample worked tickets with sample dates; replace them as needed. Follow-up alerts use today's date, so they change daily.

Sheet Support Tracker
A1: International Customer Support Tracker
A2: Fictional company: GlobeCart (global online store). Yellow cells = type or pick from dropdown. Grey cells = automatic formulas (do not type). Rows 5-10 are sample worked tickets; rows 11-24 are New tickets to work on.
A4: Ticket ID | B4: Date Logged | C4: Customer ID | D4: Customer Name | E4: Country | F4: Channel | G4: Issue Category | H4: Issue Summary | I4: Priority | J4: Ticket Status | K4: Assigned Agent | L4: Resolution / Action Taken | M4: Escalated? (Yes/No) | N4: Escalation Details (Team & Reason) | O4: Follow-up Date | P4: Date Resolved | Q4: Days Open | R4: SLA Target (Days) | S4: SLA Status | T4: Follow-up Alert
A5: TKT-001 | B5: 46296 | C5: CUST-1001 | D5: Emily Carter | E5: USA | F5: Email | G5: Billing & Payments | H5: Double charge of $129.99 on order #48213 | I5: High | J5: Resolved | K5: Agent 1 | L5: Confirmed duplicate capture. Refunded $129.99 and emailed confirmation (5-7 business days). | M5: No | O5: 46303 | P5: 46297 | Q5: =IF(B5="","",IF(P5<>"",P5-B5,TODAY()-B5)) -> 1 | R5: =IF(I5="","",INDEX(SLA_Days,MATCH(I5,Priority_List,0))) -> 2 | S5: =IF(OR(Q5="",R5=""),"",IF(P5<>"",IF(Q5<=R5,"Met","Breached"),IF(Q5>R5,"Breached - Still Open","On Track"))) -> Met | T5: =IF(C5="","",IF(OR(J5="Resolved",J5="Closed"),"Done",IF(O5="","No follow-up set",IF(O5<TODAY(),"OVERDUE",IF(O5=TODAY(),"Due Today","Upcoming"))))) -> Done
A6: TKT-002 | B6: 46296 | C6: CUST-1002 | D6: James Whitfield | E6: United Kingdom | F6: Live Chat | G6: Shipping & Delivery | H6: Parcel stuck at customs for 3 weeks | I6: Medium | J6: In Progress | K6: Agent 2 | L6: Contacted carrier; awaiting customs release. Customer informed about duty/VAT process. | M6: No | O6: 46309 | Q6: =IF(B6="","",IF(P6<>"",P6-B6,TODAY()-B6)) -> 9 | R6: =IF(I6="","",INDEX(SLA_Days,MATCH(I6,Priority_List,0))) -> 3 | S6: =IF(OR(Q6="",R6=""),"",IF(P6<>"",IF(Q6<=R6,"Met","Breached"),IF(Q6>R6,"Breached - Still Open","On Track"))) -> Breached - Still Open | T6: =IF(C6="","",IF(OR(J6="Resolved",J6="Closed"),"Done",IF(O6="","No follow-up set",IF(O6<TODAY(),"OVERDUE",IF(O6=TODAY(),"Due Today","Upcoming"))))) -> Upcoming
A7: TKT-003 | B7: 46297 | C7: CUST-1003 | D7: Anna Schneider | E7: Germany | F7: Email | G7: Data Privacy & Security | H7: GDPR request to delete personal data | I7: High | J7: Escalated | K7: Agent 1 | L7: Identity verified; request logged and forwarded. Customer told to expect reply within 30 days. | M7: Yes | N7: Data Protection Officer - GDPR deletion, legal deadline applies | O7: 46303 | Q7: =IF(B7="","",IF(P7<>"",P7-B7,TODAY()-B7)) -> 8 | R7: =IF(I7="","",INDEX(SLA_Days,MATCH(I7,Priority_List,0))) -> 2 | S7: =IF(OR(Q7="",R7=""),"",IF(P7<>"",IF(Q7<=R7,"Met","Breached"),IF(Q7>R7,"Breached - Still Open","On Track"))) -> Breached - Still Open | T7: =IF(C7="","",IF(OR(J7="Resolved",J7="Closed"),"Done",IF(O7="","No follow-up set",IF(O7<TODAY(),"OVERDUE",IF(O7=TODAY(),"Due Today","Upcoming"))))) -> OVERDUE
A8: TKT-004 | B8: 46298 | C8: CUST-1004 | D8: Haruto Tanaka | E8: Japan | F8: Email | G8: Product Defect | H8: Item scratched and packaging damaged | I8: Medium | J8: Pending Customer | K8: Agent 3 | L8: Formal apology sent. Asked customer for photos of item and packaging. | M8: No | O8: 46307 | Q8: =IF(B8="","",IF(P8<>"",P8-B8,TODAY()-B8)) -> 7 | R8: =IF(I8="","",INDEX(SLA_Days,MATCH(I8,Priority_List,0))) -> 3 | S8: =IF(OR(Q8="",R8=""),"",IF(P8<>"",IF(Q8<=R8,"Met","Breached"),IF(Q8>R8,"Breached - Still Open","On Track"))) -> Breached - Still Open | T8: =IF(C8="","",IF(OR(J8="Resolved",J8="Closed"),"Done",IF(O8="","No follow-up set",IF(O8<TODAY(),"OVERDUE",IF(O8=TODAY(),"Due Today","Upcoming"))))) -> Upcoming
A9: TKT-005 | B9: 46298 | C9: CUST-1005 | D9: Fatima Al-Mansoori | E9: United Arab Emirates | F9: WhatsApp | G9: Returns & Refunds | H9: Refund not received 10 days after return | I9: High | J9: Resolved | K9: Agent 2 | L9: Return received at warehouse; refund expedited. Reference number shared on WhatsApp. | M9: No | O9: 46304 | P9: 46300 | Q9: =IF(B9="","",IF(P9<>"",P9-B9,TODAY()-B9)) -> 2 | R9: =IF(I9="","",INDEX(SLA_Days,MATCH(I9,Priority_List,0))) -> 2 | S9: =IF(OR(Q9="",R9=""),"",IF(P9<>"",IF(Q9<=R9,"Met","Breached"),IF(Q9>R9,"Breached - Still Open","On Track"))) -> Met | T9: =IF(C9="","",IF(OR(J9="Resolved",J9="Closed"),"Done",IF(O9="","No follow-up set",IF(O9<TODAY(),"OVERDUE",IF(O9=TODAY(),"Due Today","Upcoming"))))) -> Done
A10: TKT-006 | B10: 46300 | C10: CUST-1006 | D10: Lucas Almeida | E10: Brazil | F10: Live Chat | G10: Account & Login | H10: Cannot log in - OTP code not arriving | I10: Medium | J10: Open | K10: Agent 3 | L10: Identity verified via email; checking registered phone number. | M10: No | O10: 46305 | Q10: =IF(B10="","",IF(P10<>"",P10-B10,TODAY()-B10)) -> 5 | R10: =IF(I10="","",INDEX(SLA_Days,MATCH(I10,Priority_List,0))) -> 3 | S10: =IF(OR(Q10="",R10=""),"",IF(P10<>"",IF(Q10<=R10,"Met","Breached"),IF(Q10>R10,"Breached - Still Open","On Track"))) -> Breached - Still Open | T10: =IF(C10="","",IF(OR(J10="Resolved",J10="Closed"),"Done",IF(O10="","No follow-up set",IF(O10<TODAY(),"OVERDUE",IF(O10=TODAY(),"Due Today","Upcoming"))))) -> Due Today
A11: TKT-007 | B11: 46301 | C11: CUST-1007 | D11: Olivia Brown | E11: Australia | F11: Email | G11: Order Changes & Cancellation | H11: Wants to cancel order that has shipped | I11: Low | J11: New | Q11: =IF(B11="","",IF(P11<>"",P11-B11,TODAY()-B11)) -> 4 | R11: =IF(I11="","",INDEX(SLA_Days,MATCH(I11,Priority_List,0))) -> 5 | S11: =IF(OR(Q11="",R11=""),"",IF(P11<>"",IF(Q11<=R11,"Met","Breached"),IF(Q11>R11,"Breached - Still Open","On Track"))) -> On Track | T11: =IF(C11="","",IF(OR(J11="Resolved",J11="Closed"),"Done",IF(O11="","No follow-up set",IF(O11<TODAY(),"OVERDUE",IF(O11=TODAY(),"Due Today","Upcoming"))))) -> No follow-up set
A12: TKT-008 | B12: 46301 | C12: CUST-1008 | D12: Camille Laurent | E12: France | F12: Social Media | G12: Complaint / Feedback | H12: Public complaint - order late 3rd time | I12: High | J12: New | Q12: =IF(B12="","",IF(P12<>"",P12-B12,TODAY()-B12)) -> 4 | R12: =IF(I12="","",INDEX(SLA_Days,MATCH(I12,Priority_List,0))) -> 2 | S12: =IF(OR(Q12="",R12=""),"",IF(P12<>"",IF(Q12<=R12,"Met","Breached"),IF(Q12>R12,"Breached - Still Open","On Track"))) -> Breached - Still Open | T12: =IF(C12="","",IF(OR(J12="Resolved",J12="Closed"),"Done",IF(O12="","No follow-up set",IF(O12<TODAY(),"OVERDUE",IF(O12=TODAY(),"Due Today","Upcoming"))))) -> No follow-up set
A13: TKT-009 | B13: 46302 | C13: CUST-1009 | D13: Rohan Mehta | E13: India | F13: Phone | G13: Shipping & Delivery | H13: Wrong gift item delivered before wedding | I13: High | J13: New | Q13: =IF(B13="","",IF(P13<>"",P13-B13,TODAY()-B13)) -> 3 | R13: =IF(I13="","",INDEX(SLA_Days,MATCH(I13,Priority_List,0))) -> 2 | S13: =IF(OR(Q13="",R13=""),"",IF(P13<>"",IF(Q13<=R13,"Met","Breached"),IF(Q13>R13,"Breached - Still Open","On Track"))) -> Breached - Still Open | T13: =IF(C13="","",IF(OR(J13="Resolved",J13="Closed"),"Done",IF(O13="","No follow-up set",IF(O13<TODAY(),"OVERDUE",IF(O13=TODAY(),"Due Today","Upcoming"))))) -> No follow-up set
A14: TKT-010 | B14: 46302 | C14: CUST-1010 | D14: Sophie Tremblay | E14: Canada | F14: Email | G14: Technical Support | H14: Wireless speaker stopped charging | I14: Medium | J14: New | Q14: =IF(B14="","",IF(P14<>"",P14-B14,TODAY()-B14)) -> 3 | R14: =IF(I14="","",INDEX(SLA_Days,MATCH(I14,Priority_List,0))) -> 3 | S14: =IF(OR(Q14="",R14=""),"",IF(P14<>"",IF(Q14<=R14,"Met","Breached"),IF(Q14>R14,"Breached - Still Open","On Track"))) -> On Track | T14: =IF(C14="","",IF(OR(J14="Resolved",J14="Closed"),"Done",IF(O14="","No follow-up set",IF(O14<TODAY(),"OVERDUE",IF(O14=TODAY(),"Due Today","Upcoming"))))) -> No follow-up set
A15: TKT-011 | B15: 46303 | C15: CUST-1011 | D15: Carlos Hernandez | E15: Mexico | F15: Email | G15: Shipping & Delivery | H15: Spanish-speaking customer asking for order status | I15: Low | J15: New | Q15: =IF(B15="","",IF(P15<>"",P15-B15,TODAY()-B15)) -> 2 | R15: =IF(I15="","",INDEX(SLA_Days,MATCH(I15,Priority_List,0))) -> 5 | S15: =IF(OR(Q15="",R15=""),"",IF(P15<>"",IF(Q15<=R15,"Met","Breached"),IF(Q15>R15,"Breached - Still Open","On Track"))) -> On Track | T15: =IF(C15="","",IF(OR(J15="Resolved",J15="Closed"),"Done",IF(O15="","No follow-up set",IF(O15<TODAY(),"OVERDUE",IF(O15=TODAY(),"Due Today","Upcoming"))))) -> No follow-up set
A16: TKT-012 | B16: 46303 | C16: CUST-1012 | D16: Thabo Nkosi | E16: South Africa | F16: Phone | G16: Data Privacy & Security | H16: Unauthorized orders on account (suspected hack) | I16: Critical | J16: New | Q16: =IF(B16="","",IF(P16<>"",P16-B16,TODAY()-B16)) -> 2 | R16: =IF(I16="","",INDEX(SLA_Days,MATCH(I16,Priority_List,0))) -> 1 | S16: =IF(OR(Q16="",R16=""),"",IF(P16<>"",IF(Q16<=R16,"Met","Breached"),IF(Q16>R16,"Breached - Still Open","On Track"))) -> Breached - Still Open | T16: =IF(C16="","",IF(OR(J16="Resolved",J16="Closed"),"Done",IF(O16="","No follow-up set",IF(O16<TODAY(),"OVERDUE",IF(O16=TODAY(),"Due Today","Upcoming"))))) -> No follow-up set
A17: TKT-013 | B17: 46303 | C17: CUST-1013 | D17: Mei Lin Tan | E17: Singapore | F17: Live Chat | G17: Technical Support | H17: Checkout page crashing on mobile | I17: Medium | J17: New | Q17: =IF(B17="","",IF(P17<>"",P17-B17,TODAY()-B17)) -> 2 | R17: =IF(I17="","",INDEX(SLA_Days,MATCH(I17,Priority_List,0))) -> 3 | S17: =IF(OR(Q17="",R17=""),"",IF(P17<>"",IF(Q17<=R17,"Met","Breached"),IF(Q17>R17,"Breached - Still Open","On Track"))) -> On Track | T17: =IF(C17="","",IF(OR(J17="Resolved",J17="Closed"),"Done",IF(O17="","No follow-up set",IF(O17<TODAY(),"OVERDUE",IF(O17=TODAY(),"Due Today","Upcoming"))))) -> No follow-up set
A18: TKT-014 | B18: 46304 | C18: CUST-1014 | D18: Giulia Romano | E18: Italy | F18: Email | G18: Billing & Payments | H18: Discount code WELCOME10 not applied | I18: Low | J18: New | Q18: =IF(B18="","",IF(P18<>"",P18-B18,TODAY()-B18)) -> 1 | R18: =IF(I18="","",INDEX(SLA_Days,MATCH(I18,Priority_List,0))) -> 5 | S18: =IF(OR(Q18="",R18=""),"",IF(P18<>"",IF(Q18<=R18,"Met","Breached"),IF(Q18>R18,"Breached - Still Open","On Track"))) -> On Track | T18: =IF(C18="","",IF(OR(J18="Resolved",J18="Closed"),"Done",IF(O18="","No follow-up set",IF(O18<TODAY(),"OVERDUE",IF(O18=TODAY(),"Due Today","Upcoming"))))) -> No follow-up set
A19: TKT-015 | B19: 46304 | C19: CUST-1015 | D19: Abdullah Al-Harbi | E19: Saudi Arabia | F19: Phone | G19: Order Changes & Cancellation | H19: Change delivery address + evening callback | I19: Medium | J19: New | Q19: =IF(B19="","",IF(P19<>"",P19-B19,TODAY()-B19)) -> 1 | R19: =IF(I19="","",INDEX(SLA_Days,MATCH(I19,Priority_List,0))) -> 3 | S19: =IF(OR(Q19="",R19=""),"",IF(P19<>"",IF(Q19<=R19,"Met","Breached"),IF(Q19>R19,"Breached - Still Open","On Track"))) -> On Track | T19: =IF(C19="","",IF(OR(J19="Resolved",J19="Closed"),"Done",IF(O19="","No follow-up set",IF(O19<TODAY(),"OVERDUE",IF(O19=TODAY(),"Due Today","Upcoming"))))) -> No follow-up set
A20: TKT-016 | B20: 46304 | C20: CUST-1016 | D20: Chidi Okafor | E20: Nigeria | F20: Email | G20: Billing & Payments | H20: Bank debited but order shows payment failed | I20: High | J20: New | Q20: =IF(B20="","",IF(P20<>"",P20-B20,TODAY()-B20)) -> 1 | R20: =IF(I20="","",INDEX(SLA_Days,MATCH(I20,Priority_List,0))) -> 2 | S20: =IF(OR(Q20="",R20=""),"",IF(P20<>"",IF(Q20<=R20,"Met","Breached"),IF(Q20>R20,"Breached - Still Open","On Track"))) -> On Track | T20: =IF(C20="","",IF(OR(J20="Resolved",J20="Closed"),"Done",IF(O20="","No follow-up set",IF(O20<TODAY(),"OVERDUE",IF(O20=TODAY(),"Due Today","Upcoming"))))) -> No follow-up set
A21: TKT-017 | B21: 46305 | C21: CUST-1017 | D21: Ji-woo Park | E21: South Korea | F21: Email | G21: Complaint / Feedback | H21: 3rd contact about faulty blender - wants manager | I21: High | J21: New | Q21: =IF(B21="","",IF(P21<>"",P21-B21,TODAY()-B21)) -> 0 | R21: =IF(I21="","",INDEX(SLA_Days,MATCH(I21,Priority_List,0))) -> 2 | S21: =IF(OR(Q21="",R21=""),"",IF(P21<>"",IF(Q21<=R21,"Met","Breached"),IF(Q21>R21,"Breached - Still Open","On Track"))) -> On Track | T21: =IF(C21="","",IF(OR(J21="Resolved",J21="Closed"),"Done",IF(O21="","No follow-up set",IF(O21<TODAY(),"OVERDUE",IF(O21=TODAY(),"Due Today","Upcoming"))))) -> No follow-up set
A22: TKT-018 | B22: 46305 | C22: CUST-1018 | D22: Pieter van Dijk | E22: Netherlands | F22: Email | G22: Billing & Payments | H22: Needs corrected invoice with VAT number | I22: Low | J22: New | Q22: =IF(B22="","",IF(P22<>"",P22-B22,TODAY()-B22)) -> 0 | R22: =IF(I22="","",INDEX(SLA_Days,MATCH(I22,Priority_List,0))) -> 5 | S22: =IF(OR(Q22="",R22=""),"",IF(P22<>"",IF(Q22<=R22,"Met","Breached"),IF(Q22>R22,"Breached - Still Open","On Track"))) -> On Track | T22: =IF(C22="","",IF(OR(J22="Resolved",J22="Closed"),"Done",IF(O22="","No follow-up set",IF(O22<TODAY(),"OVERDUE",IF(O22=TODAY(),"Due Today","Upcoming"))))) -> No follow-up set
... A24: TKT-020 | B24: 46305 | C24: CUST-1020 | D24: Elena Garcia | E24: Spain | F24: Email | G24: Returns & Refunds | H24: Return request after 45 days (policy is 30) | I24: Medium | J24: New | Q24: =IF(B24="","",IF(P24<>"",P24-B24,TODAY()-B24)) -> 0 | R24: =IF(I24="","",INDEX(SLA_Days,MATCH(I24,Priority_List,0))) -> 3 | S24: =IF(OR(Q24="",R24=""),"",IF(P24<>"",IF(Q24<=R24,"Met","Breached"),IF(Q24>R24,"Breached - Still Open","On Track"))) -> On Track | T24: =IF(C24="","",IF(OR(J24="Resolved",J24="Closed"),"Done",IF(O24="","No follow-up set",IF(O24<TODAY(),"OVERDUE",IF(O24=TODAY(),"Due Today","Upcoming"))))) -> No follow-up set
Q25: =IF(B25="","",IF(P25<>"",P25-B25,TODAY()-B25)) | R25: =IF(I25="","",INDEX(SLA_Days,MATCH(I25,Priority_List,0))) | S25: =IF(OR(Q25="",R25=""),"",IF(P25<>"",IF(Q25<=R25,"Met","Breached"),IF(Q25>R25,"Breached - Still Open","On Track"))) | T25: =IF(C25="","",IF(OR(J25="Resolved",J25="Closed"),"Done",IF(O25="","No follow-up set",IF(O25<TODAY(),"OVERDUE",IF(O25=TODAY(),"Due Today","Upcoming")))))
Q26: =IF(B26="","",IF(P26<>"",P26-B26,TODAY()-B26)) | R26: =IF(I26="","",INDEX(SLA_Days,MATCH(I26,Priority_List,0))) | S26: =IF(OR(Q26="",R26=""),"",IF(P26<>"",IF(Q26<=R26,"Met","Breached"),IF(Q26>R26,"Breached - Still Open","On Track"))) | T26: =IF(C26="","",IF(OR(J26="Resolved",J26="Closed"),"Done",IF(O26="","No follow-up set",IF(O26<TODAY(),"OVERDUE",IF(O26=TODAY(),"Due Today","Upcoming")))))
Q27: =IF(B27="","",IF(P27<>"",P27-B27,TODAY()-B27)) | R27: =IF(I27="","",INDEX(SLA_Days,MATCH(I27,Priority_List,0))) | S27: =IF(OR(Q27="",R27=""),"",IF(P27<>"",IF(Q27<=R27,"Met","Breached"),IF(Q27>R27,"Breached - Still Open","On Track"))) | T27: =IF(C27="","",IF(OR(J27="Resolved",J27="Closed"),"Done",IF(O27="","No follow-up set",IF(O27<TODAY(),"OVERDUE",IF(O27=TODAY(),"Due Today","Upcoming")))))
Q28: =IF(B28="","",IF(P28<>"",P28-B28,TODAY()-B28)) | R28: =IF(I28="","",INDEX(SLA_Days,MATCH(I28,Priority_List,0))) | S28: =IF(OR(Q28="",R28=""),"",IF(P28<>"",IF(Q28<=R28,"Met","Breached"),IF(Q28>R28,"Breached - Still Open","On Track"))) | T28: =IF(C28="","",IF(OR(J28="Resolved",J28="Closed"),"Done",IF(O28="","No follow-up set",IF(O28<TODAY(),"OVERDUE",IF(O28=TODAY(),"Due Today","Upcoming")))))
Q29: =IF(B29="","",IF(P29<>"",P29-B29,TODAY()-B29)) | R29: =IF(I29="","",INDEX(SLA_Days,MATCH(I29,Priority_List,0))) | S29: =IF(OR(Q29="",R29=""),"",IF(P29<>"",IF(Q29<=R29,"Met","Breached"),IF(Q29>R29,"Breached - Still Open","On Track"))) | T29: =IF(C29="","",IF(OR(J29="Resolved",J29="Closed"),"Done",IF(O29="","No follow-up set",IF(O29<TODAY(),"OVERDUE",IF(O29=TODAY(),"Due Today","Upcoming")))))
Q30: =IF(B30="","",IF(P30<>"",P30-B30,TODAY()-B30)) | R30: =IF(I30="","",INDEX(SLA_Days,MATCH(I30,Priority_List,0))) | S30: =IF(OR(Q30="",R30=""),"",IF(P30<>"",IF(Q30<=R30,"Met","Breached"),IF(Q30>R30,"Breached - Still Open","On Track"))) | T30: =IF(C30="","",IF(OR(J30="Resolved",J30="Closed"),"Done",IF(O30="","No follow-up set",IF(O30<TODAY(),"OVERDUE",IF(O30=TODAY(),"Due Today","Upcoming")))))
Q31: =IF(B31="","",IF(P31<>"",P31-B31,TODAY()-B31)) | R31: =IF(I31="","",INDEX(SLA_Days,MATCH(I31,Priority_List,0))) | S31: =IF(OR(Q31="",R31=""),"",IF(P31<>"",IF(Q31<=R31,"Met","Breached"),IF(Q31>R31,"Breached - Still Open","On Track"))) | T31: =IF(C31="","",IF(OR(J31="Resolved",J31="Closed"),"Done",IF(O31="","No follow-up set",IF(O31<TODAY(),"OVERDUE",IF(O31=TODAY(),"Due Today","Upcoming")))))
Q32: =IF(B32="","",IF(P32<>"",P32-B32,TODAY()-B32)) | R32: =IF(I32="","",INDEX(SLA_Days,MATCH(I32,Priority_List,0))) | S32: =IF(OR(Q32="",R32=""),"",IF(P32<>"",IF(Q32<=R32,"Met","Breached"),IF(Q32>R32,"Breached - Still Open","On Track"))) | T32: =IF(C32="","",IF(OR(J32="Resolved",J32="Closed"),"Done",IF(O32="","No follow-up set",IF(O32<TODAY(),"OVERDUE",IF(O32=TODAY(),"Due Today","Upcoming")))))
Q33: =IF(B33="","",IF(P33<>"",P33-B33,TODAY()-B33)) | R33: =IF(I33="","",INDEX(SLA_Days,MATCH(I33,Priority_List,0))) | S33: =IF(OR(Q33="",R33=""),"",IF(P33<>"",IF(Q33<=R33,"Met","Breached"),IF(Q33>R33,"Breached - Still Open","On Track"))) | T33: =IF(C33="","",IF(OR(J33="Resolved",J33="Closed"),"Done",IF(O33="","No follow-up set",IF(O33<TODAY(),"OVERDUE",IF(O33=TODAY(),"Due Today","Upcoming")))))
Q34: =IF(B34="","",IF(P34<>"",P34-B34,TODAY()-B34)) | R34: =IF(I34="","",INDEX(SLA_Days,MATCH(I34,Priority_List,0))) | S34: =IF(OR(Q34="",R34=""),"",IF(P34<>"",IF(Q34<=R34,"Met","Breached"),IF(Q34>R34,"Breached - Still Open","On Track"))) | T34: =IF(C34="","",IF(OR(J34="Resolved",J34="Closed"),"Done",IF(O34="","No follow-up set",IF(O34<TODAY(),"OVERDUE",IF(O34=TODAY(),"Due Today","Upcoming")))))
Q35: =IF(B35="","",IF(P35<>"",P35-B35,TODAY()-B35)) | R35: =IF(I35="","",INDEX(SLA_Days,MATCH(I35,Priority_List,0))) | S35: =IF(OR(Q35="",R35=""),"",IF(P35<>"",IF(Q35<=R35,"Met","Breached"),IF(Q35>R35,"Breached - Still Open","On Track"))) | T35: =IF(C35="","",IF(OR(J35="Resolved",J35="Closed"),"Done",IF(O35="","No follow-up set",IF(O35<TODAY(),"OVERDUE",IF(O35=TODAY(),"Due Today","Upcoming")))))
Q36: =IF(B36="","",IF(P36<>"",P36-B36,TODAY()-B36)) | R36: =IF(I36="","",INDEX(SLA_Days,MATCH(I36,Priority_List,0))) | S36: =IF(OR(Q36="",R36=""),"",IF(P36<>"",IF(Q36<=R36,"Met","Breached"),IF(Q36>R36,"Breached - Still Open","On Track"))) | T36: =IF(C36="","",IF(OR(J36="Resolved",J36="Closed"),"Done",IF(O36="","No follow-up set",IF(O36<TODAY(),"OVERDUE",IF(O36=TODAY(),"Due Today","Upcoming")))))
... Q204: =IF(B204="","",IF(P204<>"",P204-B204,TODAY()-B204)) | R204: =IF(I204="","",INDEX(SLA_Days,MATCH(I204,Priority_List,0))) | S204: =IF(OR(Q204="",R204=""),"",IF(P204<>"",IF(Q204<=R204,"Met","Breached"),IF(Q204>R204,"Breached - Still Open","On Track"))) | T204: =IF(C204="","",IF(OR(J204="Resolved",J204="Closed"),"Done",IF(O204="","No follow-up set",IF(O204<TODAY(),"OVERDUE",IF(O204=TODAY(),"Due Today","Upcoming")))))

Sheet Customer Scenarios
A1: Customer Scenarios - International Support Simulation
A2: 20 practice cases across 20 countries. Log each one in the Support Tracker (same Customer ID). 'Expected Handling' is the model answer - cover it up while practicing.
A4: Scenario # | B4: Customer ID | C4: Customer Name | D4: Country | E4: Language | Time Zone | F4: Channel | G4: Issue Category | H4: Suggested Priority | I4: Customer Message | J4: Challenge / Background | K4: Skills Tested | L4: Expected Handling (Model Answer) | M4: Should Escalate?
A5: 1 | B5: CUST-1001 | C5: Emily Carter | D5: USA | E5: English (US) | EST | F5: Email | G5: Billing & Payments | H5: High | I5: I was charged twice for order #48213. $129.99 shows up two times on my credit card statement. I need this fixed today. | J5: Could be a true duplicate charge or just a pre-authorization hold. Customer is anxious about overdraft. | K5: Empathy, payment knowledge, verification | L5: 1) Apologize and reassure. 2) Verify identity. 3) Check payment gateway: duplicate capture vs pending hold. 4) If duplicate, refund extra charge and quote 5-7 business days. 5) Send written confirmation. 6) Set follow-up in 3 days. | M5: No
A6: 2 | B6: CUST-1002 | C6: James Whitfield | D6: United Kingdom | E6: English (UK) | GMT | F6: Live Chat | G6: Shipping & Delivery | H6: Medium | I6: My parcel has been stuck at customs for 3 weeks. Tracking has not updated since 14 September. | J6: Delay is caused by customs, outside company control. Customer may face import duty/VAT. | K6: Expectation management, carrier coordination | L6: 1) Check tracking and carrier notes. 2) Explain the customs hold clearly. 3) Contact carrier for status. 4) Advise on duty/VAT paperwork. 5) Offer reship or refund if not cleared by an agreed date. 6) Follow up in 2 days. | M6: No
A7: 3 | B7: CUST-1003 | C7: Anna Schneider | D7: Germany | E7: German / English | CET | F7: Email | G7: Data Privacy & Security | H7: High | I7: Under GDPR I request deletion of all my personal data. Please confirm in writing. | J7: Legal deadline applies (about one month). Agent cannot approve deletion alone; some data (invoices) must be kept by law. | K7: Compliance awareness, escalation, written communication | L7: 1) Acknowledge within 24 hours. 2) Verify identity securely. 3) Do NOT promise full deletion yet. 4) Log request and escalate to Data Protection Officer. 5) Give customer the expected timeline. 6) Track follow-up date. | M7: Yes
A8: 4 | B8: CUST-1004 | C8: Haruto Tanaka | D8: Japan | E8: Japanese / English | JST | F8: Email | G8: Product Defect | H8: Medium | I8: The packaging seems to have been somewhat damaged, and the item has a small scratch. It is slightly disappointing. | J8: Indirect, understated complaint. Real dissatisfaction is higher than the wording suggests. | K8: Cultural sensitivity, formal tone, reading between the lines | L8: 1) Recognize the polite, indirect tone. 2) Apologize formally and sincerely. 3) Request photos of item and packaging. 4) Offer replacement or refund. 5) Keep language courteous; avoid blunt phrases. 6) Confirm next steps in writing. | M8: No
A9: 5 | B9: CUST-1005 | C9: Fatima Al-Mansoori | D9: United Arab Emirates | E9: Arabic / English | GST | F9: WhatsApp | G9: Returns & Refunds | H9: High | I9: I returned my order 10 days ago and still have no refund. I need an update now. | J9: Customer is impatient; refund may be delayed at the warehouse or in the payment processing stage. | K9: Order tracing, urgency handling | L9: 1) Locate return tracking and warehouse receipt. 2) Check refund status. 3) Explain the exact stage and timeline. 4) Expedite if item already received. 5) Share a refund reference number. 6) Follow up in 2 days. | M9: No
A10: 6 | B10: CUST-1006 | C10: Lucas Almeida | D10: Brazil | E10: Portuguese / English | BRT | F10: Live Chat | G10: Account & Login | H10: Medium | I10: I cannot log in. The verification code (OTP) never arrives on my phone. | J10: Registered phone number may be outdated or SMS blocked by the carrier. Security checks required before any change. | K10: Security verification, troubleshooting | L10: 1) Verify identity using an alternate method. 2) Check registered phone number. 3) Offer email-based OTP. 4) Update number only after verification. 5) Advise on carrier SMS blocks. 6) Confirm login success. | M10: No
A11: 7 | B11: CUST-1007 | C11: Olivia Brown | D11: Australia | E11: English (AU) | AEST | F11: Email | G11: Order Changes & Cancellation | H11: Low | I11: Please cancel my order #51877. I changed my mind. | J11: Order has already shipped, so a direct cancellation is not possible. | K11: Policy explanation, offering alternatives | L11: 1) Check order status. 2) Explain that in-transit orders cannot be cancelled. 3) Offer refuse-delivery or return option with return label. 4) Confirm refund will follow once the return is received. | M11: No
A12: 8 | B12: CUST-1008 | C12: Camille Laurent | D12: France | E12: French / English | CET | F12: Social Media | G12: Complaint / Feedback | H12: High | I12: Third time my order is late and support ignores me. Awful service! Never again. I'm sharing this with everyone. (Public post) | J12: Public visibility creates brand-reputation risk. Customer feels ignored. | K12: De-escalation, social media etiquette, recovery | L12: 1) Reply publicly and quickly with a short apology. 2) Move to private message. 3) Review full order history. 4) Offer a concrete fix plus goodwill gesture. 5) Escalate to Team Lead / Social Media Manager. 6) Follow up to confirm satisfaction. | M12: Yes
A13: 9 | B13: CUST-1009 | C13: Rohan Mehta | D13: India | E13: English / Hindi | IST | F13: Phone | G13: Shipping & Delivery | H13: High | I13: I ordered a gift for my sister's wedding on Friday. You delivered the wrong item! What do I do now? | J13: Time-sensitive and emotional. Replacement must arrive before the event. | K13: Urgency, problem solving, empathy | L13: 1) Empathize and apologize. 2) Verify order and confirm error. 3) Arrange express replacement and pickup of wrong item. 4) Confirm delivery date before Friday. 5) If impossible, offer refund. 6) Follow up within 24 hours. | M13: No
A14: 10 | B14: CUST-1010 | C14: Sophie Tremblay | D14: Canada | E14: English / French | EST | F14: Email | G14: Technical Support | H14: Medium | I14: The wireless speaker I bought 2 weeks ago has stopped charging. | J14: Could be user error or a hardware fault. Product is within warranty. | K14: Troubleshooting, warranty handling | L14: 1) Ask about charger and cable used. 2) Guide through basic troubleshooting. 3) Check warranty. 4) If hardware fault, offer replacement and share return (RMA) instructions. 5) Confirm resolution. | M14: No
A15: 11 | B15: CUST-1011 | C15: Carlos Hernandez | D15: Mexico | E15: Spanish (limited English) | CST | F15: Email | G15: Shipping & Delivery | H15: Low | I15: Hola, my order no come. Where is it? Please tell me. | J15: Language barrier. Customer writes in broken English. | K15: Clear simple language, using translation aids | L15: 1) Use short, simple sentences with no idioms. 2) Use approved Spanish template or translation tool. 3) Share tracking status and expected date. 4) Ask the customer to confirm they understood. 5) Keep a language note on the account. | M15: No
A16: 12 | B16: CUST-1012 | C16: Thabo Nkosi | D16: South Africa | E16: English | SAST | F16: Phone | G16: Data Privacy & Security | H16: Critical | I16: I can see 3 orders on my account that I never made. Someone has hacked it! | J16: Possible account takeover and fraud. Needs immediate containment. | K16: Crisis handling, security protocol, escalation | L16: 1) Stay calm and reassure. 2) Lock the account immediately. 3) Verify identity. 4) Stop shipment of suspicious orders. 5) Escalate to Fraud / Security team. 6) Reset credentials, recommend 2-step verification. 7) Refund fraudulent charges. | M16: Yes
... A24: 20 | B24: CUST-1020 | C24: Elena Garcia | D24: Spain | E24: Spanish / English | CET | F24: Email | G24: Returns & Refunds | H24: Medium | I24: I know it has been 45 days, but the jacket does not fit. Can you make an exception? | J24: Request is outside the 30-day return policy. | K24: Policy adherence with empathy, offering options | L24: 1) Thank her for contacting you. 2) Explain the 30-day policy kindly. 3) Offer allowed options (exchange, store credit). 4) Escalate only if beyond your authority. 5) Document the decision. | M24: No

Sheet Dashboard
A1: Support Dashboard
A2: Updates automatically from the Support Tracker.
A4: Key Metric | B4: Value
A5: Total tickets | B5: =COUNTA('Support Tracker'!$C$5:$C$204) -> 20
A6: Open tickets (not Resolved/Closed) | B6: =B5-COUNTIF('Support Tracker'!$J$5:$J$204,"Resolved")-COUNTIF('Support Tracker'!$J$5:$J$204,"Closed") -> 18
A7: Resolved / Closed tickets | B7: =COUNTIF('Support Tracker'!$J$5:$J$204,"Resolved")+COUNTIF('Support Tracker'!$J$5:$J$204,"Closed") -> 2
A8: Resolution rate | B8: =IF(B5=0,0,B7/B5) -> 0.1
A9: Escalated tickets | B9: =COUNTIF('Support Tracker'!$M$5:$M$204,"Yes") -> 1
A10: Escalation rate | B10: =IF(B5=0,0,B9/B5) -> 0.05
A11: Follow-ups OVERDUE | B11: =COUNTIF('Support Tracker'!$T$5:$T$204,"OVERDUE") -> 1
A12: Follow-ups due today | B12: =COUNTIF('Support Tracker'!$T$5:$T$204,"Due Today") -> 1
A13: SLA breached (resolved late + still open) | B13: =COUNTIF('Support Tracker'!$S$5:$S$204,"Breached*") -> 7
A14: Avg. days to resolve (resolved tickets) | B14: =IFERROR(AVERAGEIF('Support Tracker'!$P$5:$P$204,">0",'Support Tracker'!$Q$5:$Q$204),0) -> 1.5
A17: Ticket Status | B17: Count
A18: =Lists!A5 -> New | B18: =COUNTIF('Support Tracker'!$J$5:$J$204,A18) -> 14
A19: =Lists!A6 -> Open | B19: =COUNTIF('Support Tracker'!$J$5:$J$204,A19) -> 1
A20: =Lists!A7 -> In Progress | B20: =COUNTIF('Support Tracker'!$J$5:$J$204,A20) -> 1
A21: =Lists!A8 -> Pending Customer | B21: =COUNTIF('Support Tracker'!$J$5:$J$204,A21) -> 1
A22: =Lists!A9 -> Escalated | B22: =COUNTIF('Support Tracker'!$J$5:$J$204,A22) -> 1
A23: =Lists!A10 -> Resolved | B23: =COUNTIF('Support Tracker'!$J$5:$J$204,A23) -> 2
A24: =Lists!A11 -> Closed | B24: =COUNTIF('Support Tracker'!$J$5:$J$204,A24) -> 0
A27: Priority | B27: Count
A28: =Lists!B5 -> Critical | B28: =COUNTIF('Support Tracker'!$I$5:$I$204,A28) -> 1
A29: =Lists!B6 -> High | B29: =COUNTIF('Support Tracker'!$I$5:$I$204,A29) -> 7
A30: =Lists!B7 -> Medium | B30: =COUNTIF('Support Tracker'!$I$5:$I$204,A30) -> 7
A31: =Lists!B8 -> Low | B31: =COUNTIF('Support Tracker'!$I$5:$I$204,A31) -> 5
A33: Issue Category | B33: Count
A34: =Lists!D5 -> Billing & Payments | B34: =COUNTIF('Support Tracker'!$G$5:$G$204,A34) -> 4
A35: =Lists!D6 -> Shipping & Delivery | B35: =COUNTIF('Support Tracker'!$G$5:$G$204,A35) -> 3
A36: =Lists!D7 -> Product Defect | B36: =COUNTIF('Support Tracker'!$G$5:$G$204,A36) -> 1
A37: =Lists!D8 -> Returns & Refunds | B37: =COUNTIF('Support Tracker'!$G$5:$G$204,A37) -> 2
A38: =Lists!D9 -> Account & Login | B38: =COUNTIF('Support Tracker'!$G$5:$G$204,A38) -> 1
A39: =Lists!D10 -> Technical Support | B39: =COUNTIF('Support Tracker'!$G$5:$G$204,A39) -> 3
A40: =Lists!D11 -> Order Changes & Cancellation | B40: =COUNTIF('Support Tracker'!$G$5:$G$204,A40) -> 2
A41: =Lists!D12 -> Complaint / Feedback | B41: =COUNTIF('Support Tracker'!$G$5:$G$204,A41) -> 2
A42: =Lists!D13 -> Data Privacy & Security | B42: =COUNTIF('Support Tracker'!$G$5:$G$204,A42) -> 2

Sheet Lists
A1: Dropdown Lists & SLA Settings
A2: Edit the values below to change the dropdown choices in the tracker. Keep the Priority order and SLA days side by side.
A4: Ticket Status | B4: Priority | C4: Resolution SLA (Days) | D4: Issue Category | E4: Channel | F4: Yes / No
A5: New | B5: Critical | C5: 1 | D5: Billing & Payments | E5: Email | F5: Yes
A6: Open | B6: High | C6: 2 | D6: Shipping & Delivery | E6: Phone | F6: No
A7: In Progress | B7: Medium | C7: 3 | D7: Product Defect | E7: Live Chat
A8: Pending Customer | B8: Low | C8: 5 | D8: Returns & Refunds | E8: WhatsApp
A9: Escalated | D9: Account & Login | E9: Social Media
A10: Resolved | D10: Technical Support
A11: Closed | D11: Order Changes & Cancellation
D12: Complaint / Feedback
D13: Data Privacy & Security
A15: SLA days are assumptions (blue = editable input): Critical 1, High 2, Medium 3, Low 5 days to resolve.
